minchin/pelican/readers/commonmark/__init__.py
minchin/pelican/readers/commonmark/constants.py
minchin/pelican/readers/commonmark/initialize.py
minchin/pelican/readers/commonmark/reader.py
minchin/pelican/readers/commonmark/markdown/__init__.py
minchin/pelican/readers/commonmark/markdown/post_process.py
minchin/pelican/readers/commonmark/markdown/pre_process.py
minchin/pelican/readers/commonmark/utils/pelican.py
minchin/pelican/readers/commonmark/utils/reader.py
minchin/pelican/readers/commonmark/utils/regex.py
minchin_pelican_readers_commonmark-2.1.0.dist-info/METADATA
minchin_pelican_readers_commonmark-2.1.0.dist-info/WHEEL
minchin_pelican_readers_commonmark-2.1.0.dist-info/top_level.txt
minchin_pelican_readers_commonmark-2.1.0.dist-info/RECORD
