Metadata-Version: 2.4
Name: minchin.pelican.readers.commonmark
Version: 2.1.0
Summary: CommonMark Reader for Pelican (via Markdown-IT)
Author-email: William Minchin <w_minchin@hotmail.com>, "Gaige B. Paulsen" <gaige@cluetrust.com>
Maintainer-email: William Minchin <w_minchin@hotmail.com>
License-Expression: MIT
Project-URL: Bug Tracker, https://github.com/MinchinWeb/minchin.pelican.readers.commonmark/issues
Project-URL: Repository, https://github.com/MinchinWeb/minchin.pelican.readers.commonmark
Project-URL: Changelog, https://github.com/MinchinWeb/minchin.pelican.readers.commonmark/blob/master/CHANGELOG.rst
Keywords: pelican,plugin,commonmark,markdown
Classifier: Development Status :: 5 - Production/Stable
Classifier: Environment :: Plugins
Classifier: Framework :: Pelican
Classifier: Framework :: Pelican :: Plugins
Classifier: Intended Audience :: End Users/Desktop
Classifier: Operating System :: OS Independent
Classifier: Topic :: Text Processing :: Markup :: Markdown
Classifier: Topic :: Software Development :: Libraries :: Python Modules
Requires-Dist: pelican
Requires-Dist: Pygments>=2.6
Requires-Dist: markdown-it-py>=3
Requires-Dist: mdit-py-plugins>=0.5.0
Requires-Dist: beautifulsoup4
Requires-Dist: pyyaml
Requires-Dist: minchin.pelican.plugins.autoloader
Provides-Extra: dev
Requires-Dist: invoke; extra == "dev"
Requires-Dist: minchin.releaser; extra == "dev"
Requires-Dist: pip-tools; extra == "dev"
Requires-Dist: isort; extra == "dev"
Requires-Dist: black; extra == "dev"
Requires-Dist: pytest; extra == "dev"
Requires-Dist: pygments<2.19.0; extra == "dev"
Provides-Extra: lxml
Requires-Dist: lxml; extra == "lxml"
